broadcaster/__init__.py
broadcaster/_base.py
broadcaster/_backends/__init__.py
broadcaster/_backends/base.py
broadcaster/_backends/kafka.py
broadcaster/_backends/memory.py
broadcaster/_backends/postgres.py
broadcaster/_backends/redis.py
krispbroadcaster-0.3.0.data/data/LICENSE.md
krispbroadcaster-0.3.0.dist-info/LICENSE.md
krispbroadcaster-0.3.0.dist-info/METADATA
krispbroadcaster-0.3.0.dist-info/WHEEL
krispbroadcaster-0.3.0.dist-info/top_level.txt
krispbroadcaster-0.3.0.dist-info/RECORD
