Metadata-Version: 2.1
Name: krispbroadcaster
Version: 0.3.0
Summary: Simple broadcast channels.
Home-page: https://github.com/encode/broadcaster
Author: Tom Christie
Author-email: tom@tomchristie.com
License: BSD
Platform: UNKNOWN
Classifier: Development Status :: 3 - Alpha
Classifier: Environment :: Web Environment
Classifier: Intended Audience :: Developers
Classifier: License :: OSI Approved :: BSD License
Classifier: Operating System :: OS Independent
Classifier: Topic :: Internet :: WWW/HTTP
Classifier: Programming Language :: Python :: 3
Classifier: Programming Language :: Python :: 3.7
Classifier: Programming Language :: Python :: 3.8
Requires-Python: >=3.7
License-File: LICENSE.md
Provides-Extra: kafka
Requires-Dist: aiokafka ; extra == 'kafka'
Provides-Extra: postgres
Requires-Dist: asyncpg ; extra == 'postgres'
Provides-Extra: redis
Requires-Dist: aioredis ; extra == 'redis'
Provides-Extra: test
Requires-Dist: pytest ; extra == 'test'
Requires-Dist: pytest-asyncio ; extra == 'test'
